odoo8_addon_web_dom_model_classes-8.0.1.0.0-py2.7-nspkg.pth
odoo_addons/web_dom_model_classes/__openerp__.py
odoo_addons/web_dom_model_classes/__init__.py
odoo_addons/web_dom_model_classes/README.rst
odoo_addons/web_dom_model_classes/static/description/icon.png
odoo_addons/web_dom_model_classes/static/src/xml/web_widget_classes.xml
odoo8_addon_web_dom_model_classes-8.0.1.0.0.dist-info/top_level.txt
odoo8_addon_web_dom_model_classes-8.0.1.0.0.dist-info/WHEEL
odoo8_addon_web_dom_model_classes-8.0.1.0.0.dist-info/RECORD
odoo8_addon_web_dom_model_classes-8.0.1.0.0.dist-info/metadata.json
odoo8_addon_web_dom_model_classes-8.0.1.0.0.dist-info/DESCRIPTION.rst
odoo8_addon_web_dom_model_classes-8.0.1.0.0.dist-info/METADATA
odoo8_addon_web_dom_model_classes-8.0.1.0.0.dist-info/namespace_packages.txt
